[
  {"slug":"su","danishName":"SU-beregner 2026","shortPurpose":"Beregn praecist hvor meget SU du faar udbetalt om maaneden i 2026 baseret paa alder, bopael, uddannelsestype og forsoergerstatus.","targetUser":"Studerende paa ungdomsuddannelser og videregaaende uddannelser, 18+ aar, samt forsoergere","decisionAngle":"Skal jeg flytte hjemmefra for at faa udeboendesats?","situationHub":"studerende","longtailKeywords":["su 2026","studerende","udeboende","hjemmeboende","sats","stipendium","uddannelse","gymnasium","universitet","praktik"]},
  {"slug":"su-fribelob","danishName":"SU fribeloeb-beregner 2026","shortPurpose":"Beregn dit aarsfribeloeb i 2026, hvor meget du maa tjene ved siden af SU pr. maaned, og tilbagebetaling ved overskridelse.","targetUser":"Studerende med studiejob eller sommerjob","decisionAngle":"Skal jeg fravaelge SU i sommermaanederne for at tjene mere?","situationHub":"studerende","longtailKeywords":["fribeloeb","studiejob","studerende","sommerjob","ekstra timer","modregning","tjene ved siden af su","arbejde","loft","skat"]},
  {"slug":"su-laan-tilbagebetaling","danishName":"SU-laan tilbagebetaling-beregner 2026","shortPurpose":"Beregn hvornaar din SU-laan tilbagebetaling starter, antal aar og maanedlig ydelse baseret paa gaeld og rente.","targetUser":"Faerdiguddannede med SU-laan og studerende der overvejer SU-laan","decisionAngle":"Skal jeg afdrage SU-laanet ekstra hurtigt eller minimum-betale og investere differencen?","situationHub":"studerende","longtailKeywords":["su laan","tilbagebetaling","afdrag","studielaan","rente","dimittend","studiegaeld","gaeld","afdragsplan","investere"]},
  {"slug":"dagpenge","danishName":"Dagpengeberegner 2026","shortPurpose":"Beregn dagpenge som ledig medlem af a-kasse baseret paa tidligere indkomst, forsikring og forsoergerpligt.","targetUser":"Loenmodtagere der er blevet ledige eller bliver opsagt","decisionAngle":"Faar jeg maks-sats — og skal jeg vente med at melde mig ledig for beskaeftigelsestillaegget?","situationHub":"ledig-familie","longtailKeywords":["dagpenge","a-kasse","ledig","arbejdsloes","fyret","opsagt","maks sats","beskaeftigelsestillaeg","jobcenter","ydelse"]},
  {"slug":"dimittend","danishName":"Dimittenddagpenge-beregner 2026","shortPurpose":"Beregn dimittenddagpenge som nyuddannet inkl. forsoergertillaeg og den lavere sats efter 3 maaneder.","targetUser":"Nyuddannede med SU-berettiget uddannelse paa mindst 18 maaneder","decisionAngle":"Hvor meget mister jeg som ikke-forsoerger efter 3 maaneder?","situationHub":"ledig-familie","longtailKeywords":["dimittend","nyuddannet","dimittendsats","a-kasse","forsoergertillaeg","dagpenge nyuddannet","kandidat","bachelor","tilmeld a-kasse","loft"]},
  {"slug":"sygedagpenge","danishName":"Sygedagpengeberegner 2026","shortPurpose":"Beregn sygedagpenge ved sygemelding — maks-sats, arbejdsgiver vs kommune og 22-uger reglen.","targetUser":"Loenmodtagere, selvstaendige og ledige der bliver syge","decisionAngle":"Skal jeg melde mig syg eller ledig?","situationHub":"ledig-familie","longtailKeywords":["sygedagpenge","sygemelding","syg","sygefravaer","kommune","arbejdsgiver","22 uger","sygesikring","sygdom","fravaer"]},
  {"slug":"barselsdagpenge","danishName":"Barselsdagpenge 2026","shortPurpose":"Beregn barselsdagpenge pr. uge og total over orloven baseret paa indkomst og ansaettelsesform efter 24+24-modellen.","targetUser":"Vordende foraeldre der skal planlaegge orlov","decisionAngle":"Skal vi tage barsel samtidigt eller skifte? Skal jeg overdrage de 13 fleksible uger?","situationHub":"ledig-familie","longtailKeywords":["barsel","barselsdagpenge","orlov","faedreorlov","moedreorlov","24 uger","graviditet","foedsel","baby","udbetaling danmark"]},
  {"slug":"bornepenge","danishName":"Boernepenge 2026","shortPurpose":"Beregn samlet boerne- og ungeydelse pr. kvartal/maaned inkl. indkomstregulering, enlig-tilskud og flerboernstilskud.","targetUser":"Foraeldre (samboende, enlige, delt forsoerger) i 2026","decisionAngle":"Tjener jeg saa meget at boernepengene aftrappes — og kan pension hjaelpe?","situationHub":"ledig-familie","longtailKeywords":["boernepenge","ungeydelse","boerne og ungeydelse","boernetilskud","enlig forsoerger","flerboernstilskud","boern","familie","kvartal","udbetaling danmark"]},
  {"slug":"boligstoette","danishName":"Boligstoette beregner 2026","shortPurpose":"Beregn boligstoette (boligsikring eller boligydelse) baseret paa indkomst, husstand og boligtype.","targetUser":"Lejere, pensionister, enlige forsoergere, studerende og familier med lav indkomst","decisionAngle":"Har jeg ret til boligstoette, og hvor meget faar jeg konkret om maaneden?","situationHub":"bolig-flytning","longtailKeywords":["boligstoette","boligsikring","boligydelse","lejebolig","almen bolig","huslejetilskud","lavindkomst","pensionist","enlig","studerende"]},
  {"slug":"huslejebudget","danishName":"Huslejebudget beregner","shortPurpose":"Vurdér om en specifik husleje er forsvarlig baseret paa nettoloen, forbrug og andre faste udgifter — 30-33% reglen.","targetUser":"Boligsoegende lejere og foerstegangsindflyttere","decisionAngle":"Er denne bolig oekonomisk forsvarlig for mig — eller bliver jeg fattig paa leje?","situationHub":"bolig-flytning","longtailKeywords":["husleje","huslejebudget","lejebolig","raad til","raadighedsbeloeb","30 procent regel","foerstegangsindflytter","lejekontrakt","budget","udlejer"]},
  {"slug":"ejendomsvaerdiskat","danishName":"Ejendomsvaerdiskat beregner 2026","shortPurpose":"Beregn ejendomsvaerdiskat for 2026 efter boligskattereformen (0,51% og 1,40%) samt grundskyld og indefrysning.","targetUser":"Boligejere og kommende huskoebere","decisionAngle":"Hvor meget kommer min bolig til at koste i ejendomsskat hvert aar?","situationHub":"bolig-flytning","longtailKeywords":["ejendomsvaerdiskat","grundskyld","boligskat","boligskattereform","ejerbolig","huskoeb","indefrysning","pensionist","skat","ejendomsskat"]},
  {"slug":"andelsbolig","danishName":"Andelsbolig beregner 2026","shortPurpose":"Beregn maksimal andelspris og samlet maanedlig udgift inkl. boligafgift, forbrug og andelsboliglaan.","targetUser":"Andelshavere og kommende andelskoebere","decisionAngle":"Er denne andelspris lovlig, og bliver maanedlig udgift acceptabel?","situationHub":"bolig-flytning","longtailKeywords":["andelsbolig","andelspris","boligafgift","andelsboliglaan","maksimumpris","andelshaver","andelsboligforening","koebe andel","andelsboligloven","valuarvurdering"]},
  {"slug":"elpris-apparatforbrug","danishName":"Elpris og apparatforbrug-beregner","shortPurpose":"Live timepriser fra Nord Pool (DK1/DK2) plus afgifter — simuler hvad et apparat koster lige nu eller billigste time.","targetUser":"Husejere og lejere med variabel el-aftale (timepris)","decisionAngle":"Hvornaar skal jeg vaske toej, opvaske eller oplade for at spare mest?","situationHub":"hverdagsudgifter","longtailKeywords":["elpris","spotpris","timepris","nord pool","el aftale","varmepumpe","vaskemaskine","apparatforbrug","kwh","afgift"]},
  {"slug":"elbil-opladning","danishName":"Elbil opladning-beregner","shortPurpose":"Beregn pris for at oplade din elbil hjemme eller offentligt fra X% til Y% med valgt effekt og time slot.","targetUser":"Elbilejer eller koebskandidat","decisionAngle":"Skal jeg oplade hjemme natten over eller bruge en offentlig lynlader?","situationHub":"bil-transport","longtailKeywords":["elbil","opladning","oplader","lynlader","hjemmeoplader","clever","ionity","spotpris","ev","kwh"]},
  {"slug":"braendstof","danishName":"Braendstof-beregner","shortPurpose":"Beregn braendstofomkostning pr tur, maaned eller aar baseret paa forbrug, km og pumpepris.","targetUser":"Bilejere der vil budgettere koerselsomkostninger","decisionAngle":"Hvad koster denne tur, og er det billigere at koere benzin, diesel eller elbil paa lang sigt?","situationHub":"bil-transport","longtailKeywords":["braendstof","benzin","diesel","forbrug","pumpepris","km pris","koereomkostning","tur","tank","liter pr km"]},
  {"slug":"bil-totalomkostning","danishName":"Bil totalomkostning-beregner (TCO)","shortPurpose":"Total cost of ownership for en bil over 1, 3 eller 5 aar — koeb, finansiering, afgift, forsikring, vedligehold, vaerditab, braendstof, parkering.","targetUser":"Bilkoebere der vil sammenligne biler eller drivlinjer","decisionAngle":"Koster en elbil reelt mindre at eje end en benzinbil?","situationHub":"bil-transport","longtailKeywords":["bil totalomkostning","tco","aarsudgift","bil oekonomi","sammenlign biler","drivlinje","forsikring","vedligehold","vaerditab","ejerafgift"]},
  {"slug":"pension","danishName":"Pensionsberegner — prognose for udbetaling","shortPurpose":"Beregn hvad du faar udbetalt om maaneden ved pensionering inkl. folkepension, ATP og privat/arbejdsmarkedspension i nutidskroner.","targetUser":"Loenmodtagere og selvstaendige 30-67 aar","decisionAngle":"Sparer jeg nok op — eller skal jeg indbetale mere, gaa senere paa pension?","situationHub":"hverdagsudgifter","longtailKeywords":["pension","folkepension","atp","arbejdsmarkedspension","pensionsopsparing","pensionsalder","slutloen","prognose","indbetaling","nutidskroner"]},
  {"slug":"aktieskat","danishName":"Aktieskat 2026","shortPurpose":"Beregn skat paa realiseret aktiegevinst og udbytte i 2026 med progressionsgraense (27%/42%) og sammenligning med aktiesparekonto.","targetUser":"Private investorer med vaerdipapirdepot, gifte par der vil optimere","decisionAngle":"Skal jeg saelge nu eller vente til naeste aar for at holde mig under graensen?","situationHub":"hverdagsudgifter","longtailKeywords":["aktieskat","aktier","udbytte","gevinst","progressionsgraense","aktiesparekonto","27 procent","42 procent","tab","skat investering"]},
  {"slug":"efterloen","danishName":"Efterloen 2026","shortPurpose":"Beregn om du opfylder krav til efterloen og hvor meget du faar inkl. modregning af pension og skattefri praemie.","targetUser":"Personer 60-65 aar der overvejer efterloen","decisionAngle":"Er det vaerd at gaa paa efterloen nu eller arbejde 2 aar mere for skattefri praemie?","situationHub":"hverdagsudgifter","longtailKeywords":["efterloen","skattefri praemie","seniorordning","a-kasse","modregning","folkepension","tidlig tilbagetraekning","60 aar","65 aar","arbejdsmarked"]},
  {"slug":"feriepenge","danishName":"Feriepenge efter skat 2026","shortPurpose":"Beregn netto feriepenge — 12,5% af loennen som feriegodtgoerelse — efter AM-bidrag, A-skat og ferietillaeg.","targetUser":"Loenmodtagere paa timeloen, jobskiftere og offentligt ansatte","decisionAngle":"Skal jeg tage feriepenge ud nu eller vente til lavere indkomst-aar?","situationHub":"hverdagsudgifter","longtailKeywords":["feriepenge","feriegodtgoerelse","ferietillaeg","12,5 procent","jobskifte","ferie","skat feriepenge","udbetaling","timeloen","offentlig ansat"]},
  {"slug":"leasing-vs-koeb","danishName":"Privatleasing vs. koeb af bil — totalomkostning og breakeven","shortPurpose":"Sammenlign reel totalomkostning ved privatleasing og kontant-/laanefinansieret koeb over X aar inkl. vaerditab, renter, etablering og restvaerdi-risiko.","targetUser":"Bilkoebere der overvejer privatleasing kontra eje","decisionAngle":"Hvornaar er leasing billigere end koeb — og hvor mange aar skal jeg beholde en koebt bil for at vinde?","situationHub":"bil-transport","longtailKeywords":["privatleasing","leasing vs koeb","bil leasing","restvaerdi","etableringsgebyr","billaan","leje bil","leasingaftale","totalomkostning","breakeven"]},
  {"slug":"bil-vaerdtab","danishName":"Bil-vaerditab — markedsvaerdi nu og om 3/5 aar","shortPurpose":"Estimer hvad din bil er vaerd i dag og om 3 og 5 aar baseret paa maerkesegment, alder, km og drivlinje.","targetUser":"Bilejere der planlaegger salg eller bytte","decisionAngle":"Skal jeg saelge nu eller vente — og hvor meget taber jeg paa at koere et aar mere?","situationHub":"bil-transport","longtailKeywords":["bil vaerditab","markedsvaerdi","bil pris","saelge bil","bytte bil","brugtbil","afskrivning","aldersregler","km stand","resale"]},
  {"slug":"groen-ejerafgift","danishName":"Groen ejerafgift 2026","shortPurpose":"Beregn aarlig groen ejerafgift (CO2-baseret for nyere biler, brandstofeffektivitet for aeldre) plus udligningsafgift for diesel.","targetUser":"Bilejere og koebere der vil kende den aarlige afgift","decisionAngle":"Hvor meget koster afgiften pr aar — og kan jeg saenke den ved at vaelge anden drivlinje?","situationHub":"bil-transport","longtailKeywords":["groen ejerafgift","ejerafgift","co2 afgift","udligningsafgift","diesel afgift","bil afgift","periodisk afgift","skat","aarlig afgift","motorregister"]},
  {"slug":"pendlerbudget","danishName":"Pendlerbudget 2026","shortPurpose":"Beregn pendlingsomkostninger (braendstof/billet/slid + parkering) og det matchende skattefradrag efter 2026-satser.","targetUser":"Pendlere der koerer eller tager kollektiv til arbejde","decisionAngle":"Hvad bliver der reelt tilbage netto efter pendling — og loenner det sig at vaelge bil, tog eller flytte taettere paa?","situationHub":"bil-transport","longtailKeywords":["pendlerbudget","befordringsfradrag","pendling","koerselsfradrag","tog","metro","bus","kollektiv","arbejde","skattefradrag"]},
  {"slug":"flyttebudget","danishName":"Flyttebudget beregner 2026","shortPurpose":"Beregn samlet budget for din flytning inkl. flyttefirma, transport, pakkemateriale, opbevaring og adresseskift baseret paa boligstoerrelse, afstand og saeson.","targetUser":"Personer og familier der staar foran en flytning","decisionAngle":"Skal jeg hyre flyttefirma eller flytte selv — og hvor meget skal jeg saette af i alt?","situationHub":"bolig-flytning","longtailKeywords":["flyttebudget","flytning","flyttefirma","flytte selv","pakkemateriale","opbevaring","flyttebil","adresseskift","flytte regning","flyttehjaelp"]},
  {"slug":"depositum","danishName":"Depositum beregner 2026 (lejeloven)","shortPurpose":"Beregn lovligt maksimum for depositum og forudbetalt husleje efter lejeloven 2026 samt din samlede indflytningsomkostning.","targetUser":"Lejere der skal flytte ind i ny lejebolig","decisionAngle":"Er det depositum udlejer kraever lovligt — og hvor meget skal jeg laegge ud foer indflytning?","situationHub":"bolig-flytning","longtailKeywords":["depositum","forudbetalt husleje","lejeloven","indflytningsomkostning","lejekontrakt","udlejer","tre maaneders husleje","lovligt depositum","ny lejebolig","sikkerhedsstillelse"]},
  {"slug":"el-vand-varme-budget","danishName":"El, vand og varme budget 2026","shortPurpose":"Beregn forventet maanedligt forbrug af el, vand og varme i kroner baseret paa boligstoerrelse, personantal og varmekilde efter 2026-tariffer.","targetUser":"Lejere og boligejere der vil estimere forbrugsudgifter","decisionAngle":"Hvad skal jeg reelt regne med i forbrug pr maaned i denne bolig?","situationHub":"bolig-flytning","longtailKeywords":["forbrug","el vand varme","forbrugsudgifter","aconto","varmeregning","fjernvarme","vandregning","elregning","tariffer","maanedligt forbrug"]},
  {"slug":"kvm-beregner","danishName":"Kvadratmeter beregner og husleje pr m2 2026","shortPurpose":"Beregn boligens kvadratmeter (brutto og netto) og se hvor stor bolig du kan faa for X kr/md i Danmarks 10 stoerste byer 2026.","targetUser":"Boligsoegende lejere og koebere der vil sammenligne byer og priser","decisionAngle":"Hvor stor bolig kan jeg faa for mit budget — og hvilken by giver mest m2 for pengene?","situationHub":"bolig-flytning","longtailKeywords":["kvadratmeter","kvm","husleje pr m2","kvm pris","kvadratmeterberegner","bolig stoerrelse","byer","koebenhavn","aarhus","prissammenligning"]},
  {"slug":"moms-beregner","danishName":"Momsberegner 2026 (25%)","shortPurpose":"Tilfoej moms til netto, fratraek moms fra brutto, eller find netto fra brutto. Inkluderer momsindberetningsfrist for maaned/kvartal/halvaar.","targetUser":"Selvstaendige, freelancere og smaa virksomheder","decisionAngle":"Hvad koster varen ekskl. moms — og hvornaar skal jeg indberette?","situationHub":"selvstaendig","longtailKeywords":["moms","momsberegner","25 procent moms","fratraek moms","tilfoej moms","momsindberetning","cvr","skat","momsfrist","selvstaendig"]},
  {"slug":"timepris-freelancer","danishName":"Timepris-beregner 2026 — hvad skal du tage som freelancer?","shortPurpose":"Beregn minimum og anbefalet timepris ud fra oensket aarsindkomst efter skat, fakturable timer, ferie, pension, sygdom og faste omkostninger.","targetUser":"Freelancere, konsulenter og selvstaendige","decisionAngle":"Hvor meget skal jeg tage i timen for at faa samme netto som fast loen?","situationHub":"selvstaendig","longtailKeywords":["timepris","freelancer","konsulent","fakturere","timeloen","selvstaendig timepris","minimum timepris","raadgiver","fakturable timer","pension freelancer"]},
  {"slug":"faktura-generator","danishName":"Faktura-generator 2026","shortPurpose":"Generer en korrekt dansk faktura med CVR, momsspecifikation, linjeposter og betalingsbetingelser — klient-side HTML til print/PDF.","targetUser":"Freelancere og smaa virksomheder uden faktura-system","decisionAngle":"Hvordan laver jeg hurtigt en lovlig faktura uden software?","situationHub":"selvstaendig","longtailKeywords":["faktura","faktura generator","fakturere","cvr","momsspecifikation","pdf faktura","gratis faktura","betalingsbetingelser","fakturaformat","selvstaendig faktura"]},
  {"slug":"b-skat-beregner","danishName":"B-skat beregner 2026","shortPurpose":"Beregn aarlig og maanedlig B-skat ud fra forventet aarsoverskud, anden indkomst, fradrag og pension. Viser 10 rater (jan-okt, feb og dec fri).","targetUser":"Selvstaendige med B-indkomst","decisionAngle":"Hvor meget skal jeg betale i B-skat pr rate — og hvornaar?","situationHub":"selvstaendig","longtailKeywords":["b-skat","forelobig skat","selvstaendig skat","b-indkomst","rater","skat indbetaling","aarsoverskud","skattekonto","b-skat datoer","sktst"]},
  {"slug":"overskud-efter-skat","danishName":"Overskud efter skat 2026 — profit-kalkulator","shortPurpose":"Beregn virkeligt overskud efter skat ud fra omsaetning, driftsomkostninger, koerselsfradrag og loen. Sammenligner virksomhedsskatteordningen (22%) med fuld personlig beskatning.","targetUser":"Selvstaendige der vil vide bundlinjen","decisionAngle":"Skal jeg bruge virksomhedsskatteordningen eller personlig beskatning?","situationHub":"selvstaendig","longtailKeywords":["overskud efter skat","virksomhedsskatteordning","vso","personlig beskatning","selvstaendig","omsaetning","driftsomkostninger","22 procent","bundlinje","skat selvstaendig"]}
]